_gd/_gd.cp311-win_amd64.pyd
gd/__init__.py
gd/__main__.py
gd/api/__init__.py
gd/api/color_channels.py
gd/api/database/__init__.py
gd/api/database/common.py
gd/api/database/completed.py
gd/api/database/database.py
gd/api/database/statistics.py
gd/api/database/storage.py
gd/api/database/unlock_values.py
gd/api/database/values.py
gd/api/database/variables.py
gd/api/editor.py
gd/api/folder.py
gd/api/guidelines.py
gd/api/header.py
gd/api/hsv.py
gd/api/levels.py
gd/api/like.py
gd/api/objects.py
gd/api/recording.py
gd/api/rewards.py
gd/api/save_manager.py
gd/api/songs.py
gd/artist.py
gd/assets/glow_sheet.json
gd/assets/glow_sheet.png
gd/assets/icon_sheet.json
gd/assets/icon_sheet.png
gd/assets/robot_animation_sheet.json
gd/assets/spider_animation_sheet.json
gd/assets.py
gd/asyncio.py
gd/binary.py
gd/binary_constants.py
gd/binary_utils.py
gd/capacity.py
gd/client.py
gd/color.py
gd/comments.py
gd/constants.py
gd/converter.py
gd/credentials.py
gd/date_time.py
gd/decorators.py
gd/difficulty_parameters.py
gd/encoding.py
gd/entity.py
gd/enums.py
gd/errors.py
gd/events/__init__.py
gd/events/controller.py
gd/events/listeners.py
gd/filters.py
gd/friend_request.py
gd/http.py
gd/image/__init__.py
gd/image/animation.py
gd/image/converters.py
gd/image/factory.py
gd/image/geometry.py
gd/image/icon.py
gd/image/layer.py
gd/image/sheet.py
gd/image/sprite.py
gd/level.py
gd/level_packs.py
gd/main.py
gd/memory/__init__.py
gd/memory/arrays.py
gd/memory/base.py
gd/memory/cocos.py
gd/memory/constants.py
gd/memory/data.py
gd/memory/fields.py
gd/memory/gd.py
gd/memory/internal/__init__.py
gd/memory/internal/darwin.py
gd/memory/internal/utils.py
gd/memory/internal/windows.py
gd/memory/pointers.py
gd/memory/special.py
gd/memory/state.py
gd/memory/strings.py
gd/memory/utils.py
gd/message.py
gd/models.py
gd/models_constants.py
gd/models_utils.py
gd/named_dicts.py
gd/newgrounds.py
gd/official_levels.py
gd/official_songs.py
gd/password.py
gd/platform.py
gd/plist.py
gd/progress.py
gd/py.typed
gd_py-1.0.1.dist-info/entry_points.txt
gd_py-1.0.1.dist-info/LICENSE
gd_py-1.0.1.dist-info/METADATA
gd_py-1.0.1.dist-info/WHEEL
gd_py-1.0.1.dist-info/RECORD
