Metadata-Version: 2.1
Name: gd.py
Version: 1.0.1
Summary: An API wrapper for Geometry Dash written in Python.
Home-page: https://github.com/nekitdev/gd.py
License: MIT
Keywords: python,gd
Author: nekitdev
Requires-Python: >=3.7
Classifier: Development Status :: 4 - Beta
Classifier: Intended Audience :: Developers
Classifier: License :: OSI Approved :: MIT License
Classifier: Operating System :: OS Independent
Classifier: Programming Language :: Python :: 3
Classifier: Programming Language :: Python :: 3.7
Classifier: Programming Language :: Python :: 3.8
Classifier: Programming Language :: Python :: 3.9
Classifier: Programming Language :: Python :: 3.10
Classifier: Programming Language :: Python :: 3.11
Classifier: Typing :: Typed
Provides-Extra: crypto
Provides-Extra: image
Provides-Extra: server
Provides-Extra: speed
Requires-Dist: aiohttp (>=3.8.4)
Requires-Dist: async-extensions (>=1.4.1)
Requires-Dist: attrs (>=23.1.0)
Requires-Dist: cattrs (==22.2.0)
Requires-Dist: click (>=8.1.3)
Requires-Dist: colors-core (>=1.0.1)
Requires-Dist: entrypoint (>=1.4.0)
Requires-Dist: fastapi (>=0.95.2) ; extra == "server"
Requires-Dist: iters (>=0.13.1)
Requires-Dist: lxml (>=4.9.2) ; extra == "speed"
Requires-Dist: named (>=1.3.0)
Requires-Dist: pendulum (>=2.1.2)
Requires-Dist: pillow (>=9.5.0) ; extra == "image"
Requires-Dist: pycryptodome (>=3.18.0) ; extra == "crypto"
Requires-Dist: tqdm (>=4.65.0)
Requires-Dist: uvicorn[standard] (>=0.22.0) ; extra == "server"
Requires-Dist: versions (>=1.6.1)
Requires-Dist: xor-cipher (>=3.0.1)
Requires-Dist: yarl (>=1.9.2)
Project-URL: Documentation, https://nekitdev.github.io/gd.py
Project-URL: Discord, https://nekit.dev/discord
Project-URL: Funding, https://patreon.com/nekitdev
Project-URL: Issues, https://github.com/nekitdev/gd.py/issues
Project-URL: Repository, https://github.com/nekitdev/gd.py
